cfw/__init__.py
cfw/framework/__init__.py
cfw/framework/command.py
cfw/framework/discovery.py
cfw/framework/errors.py
cfw/framework/formatting.py
cfw/framework/util.py
cfw/framework/args/__init__.py
cfw/framework/args/model.py
cfw/testapp/__init__.py
cfw/testapp/test.py
cfw-0.1.14.dist-info/METADATA
cfw-0.1.14.dist-info/RECORD
cfw-0.1.14.dist-info/WHEEL
cfw-0.1.14.dist-info/top_level.txt
