Metadata-Version: 2.1
Name: cfw
Version: 0.1.14
Summary: Python Command Line Interface Library
Home-page: https://github.com/zinic/python-cfw
Author: John Hopper
Author-email: john.hopper@jpserver.net
License: MIT
Platform: UNKNOWN
